{
"metabolites":[
{"id":"1,3-Bisphospho-D-glycerate_c0","name":"1,3-Bisphospho-D-glycerate_c0","compartment":"cytoplasm","charge":"-4","formula":"C3H4O10P2","field6":"","field7":"","field8":""},
{"id":"2-Oxoglutarate_c0","name":"2-Oxoglutarate_c0","compartment":"cytoplasm","charge":"-2","formula":"C5H4O5","field6":"","field7":"","field8":""},
{"id":"3-Phosphoglycerate_c0","name":"3-Phosphoglycerate_c0","compartment":"cytoplasm","charge":"-3","formula":"C3H4O7P","field6":"","field7":"","field8":""},
{"id":"6-Phospho-D-gluconate_c0","name":"6-Phospho-D-gluconate_c0","compartment":"cytoplasm","charge":"-3","formula":"C6H10O10P","field6":"","field7":"","field8":""},
{"id":"6-phospho-D-glucono-1-5-lactone_c0","name":"6-phospho-D-glucono-1-5-lactone_c0","compartment":"cytoplasm","charge":"-2","formula":"C6H9O9P","field6":"","field7":"","field8":""},
{"id":"Acetate_c0","name":"Acetate","compartment":"cytoplasm","charge":"-1","formula":"C2H3O2","field6":"","field7":"","field8":""},
{"id":"Acetate_e0","name":"Acetate","compartment":"external","charge":"-1","formula":"C2H3O2","field6":"","field7":"","field8":""},
{"id":"Acetyl_CoA_c0","name":"Acetyl_CoA_c0","compartment":"cytoplasm","charge":"-4","formula":"C23H34N7O17P3S","field6":"","field7":"","field8":""},
{"id":"Acetylphosphate_c0","name":"Acetylphosphate_c0","compartment":"cytoplasm","charge":"-2","formula":"C2H3O5P","field6":"","field7":"","field8":""},
{"id":"ADP_c0","name":"ADP_c0","compartment":"cytoplasm","charge":"-2","formula":"C10H13N5O10P2","field6":"","field7":"","field8":""},
{"id":"ATP_c0","name":"ATP_c0","compartment":"cytoplasm","charge":"-3","formula":"C10H13N5O13P3","field6":"","field7":"","field8":""},
{"id":"Biomass_c0","name":"Biomass_c0","compartment":"cytoplasm","charge":"0","formula":"null","field6":"","field7":"","field8":""},
{"id":"Citrate_c0","name":"Citrate_c0","compartment":"cytoplasm","charge":"-3","formula":"C6H5O7","field6":"","field7":"","field8":""},
{"id":"CO2_c0","name":"CO2","compartment":"cytoplasm","charge":"0","formula":"CO2","field6":"","field7":"","field8":""},
{"id":"CO2_e0","name":"CO2","compartment":"external","charge":"0","formula":"CO2","field6":"","field7":"","field8":""},
{"id":"CoA_c0","name":"CoA_c0","compartment":"cytoplasm","charge":"-4","formula":"C21H32N7O16P3S","field6":"","field7":"","field8":""},
{"id":"cytochrome-bo-ox_c0","name":"cytochrome-bo-ox_c0","compartment":"cytoplasm","charge":"2","formula":"CuR","field6":"","field7":"","field8":""},
{"id":"cytochrome-bo-red_c0","name":"cytochrome-bo-red_c0","compartment":"cytoplasm","charge":"2","formula":"CuR","field6":"","field7":"","field8":""},
{"id":"D_Erythrose4_phosphate_c0","name":"D_Erythrose4_phosphate_c0","compartment":"cytoplasm","charge":"-2","formula":"C4H7O7P","field6":"","field7":"","field8":""},
{"id":"D_fructose_6_phosphate_c0","name":"D_fructose_6_phosphate","compartment":"cytoplasm","charge":"-2","formula":"C6H11O9P","field6":"","field7":"","field8":""},
{"id":"D_fructose1,6bisphosphate_c0","name":"D_fructose1_6bisphosphate_c0","compartment":"cytoplasm","charge":"-4","formula":"C6H10O12P2","field6":"","field7":"","field8":""},
{"id":"D_glucose_6_phosphate_c0","name":"D_glucose_6_phosphate_c0","compartment":"cytoplasm","charge":"-2","formula":"C6H11O9P","field6":"","field7":"","field8":""},
{"id":"D_Glucose_e0","name":"D_Glucose","compartment":"external","charge":"0","formula":"C6H12O6","field6":"","field7":"","field8":""},
{"id":"D_Ribulose5_phosphate_c0","name":"D_Ribulose5_phosphate_c0","compartment":"cytoplasm","charge":"-2","formula":"C5H9O8P","field6":"","field7":"","field8":""},
{"id":"D_Xylulose5_phosphate_c0","name":"D_Xylulose5_phosphate_c0","compartment":"cytoplasm","charge":"-2","formula":"C5H9O8P","field6":"","field7":"","field8":""},
{"id":"FAD_c0","name":"FAD_c0","compartment":"cytoplasm","charge":"-3","formula":"C27H30N9O15P2","field6":"","field7":"","field8":""},
{"id":"FADH2_c0","name":"FADH2_c0","compartment":"cytoplasm","charge":"-2","formula":"C27H33N9O15P2","field6":"","field7":"","field8":""},
{"id":"Fumarate_c0","name":"Fumarate","compartment":"cytoplasm","charge":"-2","formula":"C4H2O4","field6":"","field7":"","field8":""},
{"id":"Fumarate_e0","name":"Fumarate","compartment":"external","charge":"-2","formula":"C4H2O4","field6":"","field7":"","field8":""},
{"id":"Glyceraldehyde3_phosphate_c0","name":"Glyceraldehyde3_phosphate_c0","compartment":"cytoplasm","charge":"-2","formula":"C3H5O6P","field6":"","field7":"","field8":""},
{"id":"Glycerone_phosphate_c0","name":"Glycerone_phosphate_c0","compartment":"cytoplasm","charge":"-2","formula":"C3H5O6P","field6":"","field7":"","field8":""},
{"id":"H_c0","name":"H","compartment":"cytoplasm","charge":"1","formula":"H","field6":"","field7":"","field8":""},
{"id":"H_e0","name":"H","compartment":"external","charge":"1","formula":"H","field6":"","field7":"","field8":""},
{"id":"H2CO3_c0","name":"H2CO3_c0","compartment":"cytoplasm","charge":"-1","formula":"CHO3","field6":"","field7":"","field8":""},
{"id":"H2O_c0","name":"H2O","compartment":"cytoplasm","charge":"0","formula":"H2O","field6":"","field7":"","field8":""},
{"id":"H2O_e0","name":"H2O","compartment":"external","charge":"0","formula":"H2O","field6":"","field7":"","field8":""},
{"id":"Isocitrate_c0","name":"Isocitrate_c0","compartment":"cytoplasm","charge":"-3","formula":"C6H5O7","field6":"","field7":"","field8":""},
{"id":"L_Malate_c0","name":"L_Malate_c0","compartment":"cytoplasm","charge":"-2","formula":"C4H4O5","field6":"","field7":"","field8":""},
{"id":"Menaquinol8_c0","name":"Menaquinol8","compartment":"cytoplasm","charge":"0","formula":"C51H74O2","field6":"","field7":"","field8":""},
{"id":"Menaquinone8_c0","name":"Menaquinone8","compartment":"cytoplasm","charge":"0","formula":"C51H72O2","field6":"","field7":"","field8":""},
{"id":"Na_c0","name":"Na","compartment":"cytoplasm","charge":"1","formula":"Na","field6":"","field7":"","field8":""},
{"id":"Na_e0","name":"Na","compartment":"external","charge":"1","formula":"Na","field6":"","field7":"","field8":""},
{"id":"NAD_c0","name":"NAD_c0","compartment":"cytoplasm","charge":"-1","formula":"C21H26N7O14P2","field6":"","field7":"","field8":""},
{"id":"NADH_c0","name":"NADH_c0","compartment":"cytoplasm","charge":"-2","formula":"C21H27N7O14P2","field6":"","field7":"","field8":""},
{"id":"NADP_c0","name":"NADP_c0","compartment":"cytoplasm","charge":"-3","formula":"C21H25N7O17P3","field6":"","field7":"","field8":""},
{"id":"NADPH_c0","name":"NADPH_c0","compartment":"cytoplasm","charge":"-4","formula":"C21H26N7O17P3","field6":"","field7":"","field8":""},
{"id":"O2_c0","name":"O2","compartment":"cytoplasm","charge":"0","formula":"O2","field6":"","field7":"","field8":""},
{"id":"O2_e0","name":"O2","compartment":"external","charge":"0","formula":"O2","field6":"","field7":"","field8":""},
{"id":"Oxaloacetate_c0","name":"Oxaloacetate_c0","compartment":"cytoplasm","charge":"-2","formula":"C4H2O5","field6":"","field7":"","field8":""},
{"id":"Oxalosuccinate_c0","name":"Oxalosuccinate_c0","compartment":"cytoplasm","charge":"-3","formula":"C6H3O7","field6":"","field7":"","field8":""},
{"id":"Oxidizedferredoxin_c0","name":"Oxidizedferredoxin_c0","compartment":"cytoplasm","charge":"6","formula":"Fe2R4S6","field6":"","field7":"","field8":""},
{"id":"Phosphate_c0","name":"Phosphate_c0","compartment":"cytoplasm","charge":"-2","formula":"HO4P","field6":"","field7":"","field8":""},
{"id":"Phosphate_e0","name":"Phosphate_e0","compartment":"external","charge":"-2","formula":"HO4P","field6":"","field7":"","field8":""},
{"id":"Phosphoenolpyruvate_c0","name":"Phosphoenolpyruvate_c0","compartment":"cytoplasm","charge":"-3","formula":"C3H2O6P","field6":"","field7":"","field8":""},
{"id":"Pyruvate_c0","name":"Pyruvate_c0","compartment":"cytoplasm","charge":"-1","formula":"C3H3O3","field6":"","field7":"","field8":""},
{"id":"Reducedferredoxin_c0","name":"Reducedferredoxin_c0","compartment":"cytoplasm","charge":"4","formula":"Fe2R4S6","field6":"","field7":"","field8":""},
{"id":"ribose_5_phosphate_c0","name":"ribose_5_phosphate_c0","compartment":"cytoplasm","charge":"-2","formula":"C5H9O8P","field6":"","field7":"","field8":""},
{"id":"Sedoheptulose7_phosphate_c0","name":"Sedoheptulose7_phosphate_c0","compartment":"cytoplasm","charge":"-2","formula":"C7H13O10P","field6":"","field7":"","field8":""},
{"id":"Succinate_c0","name":"Succinate_c0","compartment":"cytoplasm","charge":"-2","formula":"C4H4O4","field6":"","field7":"","field8":""},
{"id":"Ubiquinol_c0","name":"Ubiquinol_c0","compartment":"cytoplasm","charge":"0","formula":"C49H76O4","field6":"","field7":"","field8":""},
{"id":"Ubiquinone_c0","name":"Ubiquinone_c0","compartment":"cytoplasm","charge":"0","formula":"C49H74O4","field6":"","field7":"","field8":""},
{"id":"Ethanol_c0","name":"Ethanol_c0","compartment":"cytoplasm","charge":"0","formula":"C2H6O","field6":"","field7":"","field8":""},
{"id":"Ethanol_e0","name":"Ethanol_e0","compartment":"external","charge":"0","formula":"C2H6O","field6":"","field7":"","field8":""},
{"id":"2-Phospho-D-glycerate_c0","name":"2-Phospho-D-glycerate_c0","compartment":"cytoplasm","charge":"-3","formula":"C3H4O7P","field6":"","field7":"","field8":""},
{"id":"Acetaldehyde_c0","name":"Acetaldehyde_c0","compartment":"cytoplasm","charge":"0","formula":"C2H4O","field6":"","field7":"","field8":""},
{"id":"2-Keto-3-deoxy-6-phosphogluconate_c0","name":"2-Keto-3-deoxy-6-phosphogluconate_c0","compartment":"cytoplasm","charge":"-3","formula":"C6H8O9P","field6":"","field7":"","field8":""},
{"id":"","name":"","compartment":"","charge":"","formula":"","field6":"","field7":"","field8":""},
{"id":"","name":"","compartment":"","charge":"","formula":"","field6":"","field7":"","field8":""},
{"id":"","name":"","compartment":"","charge":"","formula":"","field6":"","field7":"","field8":""},
{"id":"","name":"","compartment":"","charge":"","formula":"","field6":"","field7":"","field8":""},
{"id":"","name":"","compartment":"","charge":"","formula":"","field6":"","field7":"","field8":""},
{"id":"","name":"","compartment":"","charge":"","formula":"","field6":"","field7":"","field8":""},
{"id":"","name":"","compartment":"","charge":"","formula":"","field6":"","field7":"","field8":""},
{"id":"","name":"","compartment":"","charge":"","formula":"","field6":"","field7":"","field8":""},
{"id":"","name":"","compartment":"","charge":"","formula":"","field6":"","field7":"","field8":""},
{"id":"","name":"","compartment":"","charge":"","formula":"","field6":"","field7":"","field8":""},
{"id":"","name":"","compartment":"","charge":"","formula":"","field6":"","field7":"","field8":""},
{"id":"","name":"","compartment":"","charge":"","formula":"","field6":"","field7":"","field8":""},
{"id":"","name":"","compartment":"","charge":"","formula":"","field6":"","field7":"","field8":""},
{"id":"","name":"","compartment":"","charge":"","formula":"","field6":"","field7":"","field8":""},
{"id":"","name":"","compartment":"","charge":"","formula":"","field6":"","field7":"","field8":""},
{"id":"","name":"","compartment":"","charge":"","formula":"","field6":"","field7":"","field8":""},
{"id":"","name":"","compartment":"","charge":"","formula":"","field6":"","field7":"","field8":""},
{"id":"","name":"","compartment":"","charge":"","formula":"","field6":"","field7":"","field8":""},
{"id":"","name":"","compartment":"","charge":"","formula":"","field6":"","field7":"","field8":""},
{"id":"","name":"","compartment":"","charge":"","formula":"","field6":"","field7":"","field8":""},
{"id":"","name":"","compartment":"","charge":"","formula":"","field6":"","field7":"","field8":""},
{"id":"","name":"","compartment":"","charge":"","formula":"","field6":"","field7":"","field8":""},
{"id":"","name":"","compartment":"","charge":"","formula":"","field6":"","field7":"","field8":""},
{"id":"","name":"","compartment":"","charge":"","formula":"","field6":"","field7":"","field8":""},
{"id":"","name":"","compartment":"","charge":"","formula":"","field6":"","field7":"","field8":""},
{"id":"","name":"","compartment":"","charge":"","formula":"","field6":"","field7":"","field8":""},
{"id":"","name":"","compartment":"","charge":"","formula":"","field6":"","field7":"","field8":""},
{"id":"","name":"","compartment":"","charge":"","formula":"","field6":"","field7":"","field8":""},
{"id":"","name":"","compartment":"","charge":"","formula":"","field6":"","field7":"","field8":""},
{"id":"","name":"","compartment":"","charge":"","formula":"","field6":"","field7":"","field8":""},
{"id":"","name":"","compartment":"","charge":"","formula":"","field6":"","field7":"","field8":""},
{"id":"","name":"","compartment":"","charge":"","formula":"","field6":"","field7":"","field8":""},
{"id":"","name":"","compartment":"","charge":"","formula":"","field6":"","field7":"","field8":""},
{"id":"","name":"","compartment":"","charge":"","formula":"","field6":"","field7":"","field8":""},
{"id":"","name":"","compartment":"","charge":"","formula":"","field6":"","field7":"","field8":""},
{"id":"","name":"","compartment":"","charge":"","formula":"","field6":"","field7":"","field8":""},
{"id":"","name":"","compartment":"","charge":"","formula":"","field6":"","field7":"","field8":""},
{"id":"","name":"","compartment":"","charge":"","formula":"","field6":"","field7":"","field8":""},
{"id":"","name":"","compartment":"","charge":"","formula":"","field6":"","field7":"","field8":""},
{"id":"","name":"","compartment":"","charge":"","formula":"","field6":"","field7":"","field8":""},
{"id":"","name":"","compartment":"","charge":"","formula":"","field6":"","field7":"","field8":""},
{"id":"","name":"","compartment":"","charge":"","formula":"","field6":"","field7":"","field8":""},
{"id":"","name":"","compartment":"","charge":"","formula":"","field6":"","field7":"","field8":""},
{"id":"","name":"","compartment":"","charge":"","formula":"","field6":"","field7":"","field8":""},
{"id":"","name":"","compartment":"","charge":"","formula":"","field6":"","field7":"","field8":""},
{"id":"","name":"","compartment":"","charge":"","formula":"","field6":"","field7":"","field8":""},
{"id":"","name":"","compartment":"","charge":"","formula":"","field6":"","field7":"","field8":""},
{"id":"","name":"","compartment":"","charge":"","formula":"","field6":"","field7":"","field8":""},
{"id":"","name":"","compartment":"","charge":"","formula":"","field6":"","field7":"","field8":""},
{"id":"","name":"","compartment":"","charge":"","formula":"","field6":"","field7":"","field8":""},
{"id":"","name":"","compartment":"","charge":"","formula":"","field6":"","field7":"","field8":""},
{"id":"","name":"","compartment":"","charge":"","formula":"","field6":"","field7":"","field8":""},
{"id":"","name":"","compartment":"","charge":"","formula":"","field6":"","field7":"","field8":""},
{"id":"","name":"","compartment":"","charge":"","formula":"","field6":"","field7":"","field8":""},
{"id":"","name":"","compartment":"","charge":"","formula":"","field6":"","field7":"","field8":""},
{"id":"","name":"","compartment":"","charge":"","formula":"","field6":"","field7":"","field8":""},
{"id":"","name":"","compartment":"","charge":"","formula":"","field6":"","field7":"","field8":""},
{"id":"","name":"","compartment":"","charge":"","formula":"","field6":"-188.9","field7":"C00026","field8":"cpd00024"},
{"id":"","name":"","compartment":"","charge":"","formula":"","field6":"-371.9","field7":"C00197","field8":"cpd00169"},
{"id":"","name":"","compartment":"","charge":"","formula":"","field6":"-481.16","field7":"C00345","field8":"cpd00284"},
{"id":"","name":"","compartment":"","charge":"","formula":"","field6":"-428.52","field7":"C01236","field8":"cpd00911"},
{"id":"","name":"","compartment":"","charge":"","formula":"","field6":"","field7":"","field8":"cpd18077"},
{"id":"","name":"","compartment":"","charge":"","formula":"","field6":"","field7":"","field8":"cpd18078"}
]
