{
    "metadata": [
        [
            767,
            "Carbon-Gelatin",
            "KBaseBiochem.Media-1.0",
            "2021-07-16T17:49:17+0000",
            1,
            "anabcoelho",
            79695,
            "anabcoelho:narrative_1608212258873",
            "e1f506ca8de0aea6081e52ca8fd8ded3",
            2043,
            {}
        ]
    ],
    "provenance": [
        {
            "copied": "262/141/1",
            "copy_source_inaccessible": 0,
            "created": "2014-01-18T09:35:45+0000",
            "creator": "chenry",
            "epoch": 1390037745866,
            "extracted_ids": {},
            "info": [
                767,
                "Carbon-Gelatin",
                "KBaseBiochem.Media-1.0",
                "2021-07-16T17:49:17+0000",
                1,
                "anabcoelho",
                79695,
                "anabcoelho:narrative_1608212258873",
                "e1f506ca8de0aea6081e52ca8fd8ded3",
                2043,
                {}
            ],
            "path": [
                "79695/767/1"
            ],
            "provenance": [
                {
                    "custom": {},
                    "epoch": 1371747861000,
                    "external_data": [],
                    "input_ws_objects": [],
                    "intermediate_incoming": [],
                    "intermediate_outgoing": [],
                    "method": "load_media_from_bio",
                    "method_params": [],
                    "resolved_ws_objects": [],
                    "service": "KBaseFBAModeling",
                    "service_ver": "0",
                    "subactions": [],
                    "time": "2013-06-20T17:04:21+0000"
                }
            ],
            "refs": []
        }
    ]
}