{
    "metadata": [
        [
            625,
            "Carbon-Dextrin",
            "KBaseBiochem.Media-1.0",
            "2021-06-02T16:44:33+0000",
            1,
            "anabcoelho",
            79695,
            "anabcoelho:narrative_1608212258873",
            "7df9d1074bb13a8b5997c04cf0fbe3ed",
            2043,
            {}
        ]
    ],
    "provenance": [
        {
            "copied": "262/104/1",
            "copy_source_inaccessible": 0,
            "created": "2014-01-18T09:26:05+0000",
            "creator": "chenry",
            "epoch": 1390037165239,
            "extracted_ids": {},
            "info": [
                625,
                "Carbon-Dextrin",
                "KBaseBiochem.Media-1.0",
                "2021-06-02T16:44:33+0000",
                1,
                "anabcoelho",
                79695,
                "anabcoelho:narrative_1608212258873",
                "7df9d1074bb13a8b5997c04cf0fbe3ed",
                2043,
                {}
            ],
            "path": [
                "79695/625/1"
            ],
            "provenance": [
                {
                    "custom": {},
                    "epoch": 1371747862000,
                    "external_data": [],
                    "input_ws_objects": [],
                    "intermediate_incoming": [],
                    "intermediate_outgoing": [],
                    "method": "load_media_from_bio",
                    "method_params": [],
                    "resolved_ws_objects": [],
                    "service": "KBaseFBAModeling",
                    "service_ver": "0",
                    "subactions": [],
                    "time": "2013-06-20T17:04:22+0000"
                }
            ],
            "refs": []
        }
    ]
}