{
    "metadata": [
        [
            618,
            "Carbon-D-Serine",
            "KBaseBiochem.Media-1.0",
            "2021-06-02T16:36:10+0000",
            1,
            "anabcoelho",
            79695,
            "anabcoelho:narrative_1608212258873",
            "ebd3e118ea9c20f16820ec7dc9c1b1b6",
            2045,
            {}
        ]
    ],
    "provenance": [
        {
            "copied": "262/143/1",
            "copy_source_inaccessible": 0,
            "created": "2014-01-18T09:36:17+0000",
            "creator": "chenry",
            "epoch": 1390037777409,
            "extracted_ids": {},
            "info": [
                618,
                "Carbon-D-Serine",
                "KBaseBiochem.Media-1.0",
                "2021-06-02T16:36:10+0000",
                1,
                "anabcoelho",
                79695,
                "anabcoelho:narrative_1608212258873",
                "ebd3e118ea9c20f16820ec7dc9c1b1b6",
                2045,
                {}
            ],
            "path": [
                "79695/618/1"
            ],
            "provenance": [
                {
                    "custom": {},
                    "epoch": 1371747862000,
                    "external_data": [],
                    "input_ws_objects": [],
                    "intermediate_incoming": [],
                    "intermediate_outgoing": [],
                    "method": "load_media_from_bio",
                    "method_params": [],
                    "resolved_ws_objects": [],
                    "service": "KBaseFBAModeling",
                    "service_ver": "0",
                    "subactions": [],
                    "time": "2013-06-20T17:04:22+0000"
                }
            ],
            "refs": []
        }
    ]
}